ispdb.py
setup.py
ispdb.egg-info/PKG-INFO
ispdb.egg-info/SOURCES.txt
ispdb.egg-info/dependency_links.txt
ispdb.egg-info/requires.txt
ispdb.egg-info/top_level.txt
test/test_ispdb.py