Metadata-Version: 1.1
Name: ispdb
Version: 0.2
Summary: Interface to Mozilla ISP database
Home-page: UNKNOWN
Author: sprt
Author-email: hellosprt@gmail.com
License: Copyright (C) 2013 sprt
